eda_and_beyond/__init__.py
eda_and_beyond/eda_tools.py
eda_and_beyond/modeling_tools.py
tests/__init__.py
tests/test_eda_tools.py
eda_and_beyond-0.0.1.dist-info/LICENSE
eda_and_beyond-0.0.1.dist-info/METADATA
eda_and_beyond-0.0.1.dist-info/WHEEL
eda_and_beyond-0.0.1.dist-info/top_level.txt
eda_and_beyond-0.0.1.dist-info/RECORD
