Metadata-Version: 2.1
Name: eda-and-beyond
Version: 0.0.1
Summary: A package of automation tools for EDA and modeling
Home-page: https://github.com/FredaXin/eda_and_beyond
Author: Freda Xin
Author-email: freda.xin@gmail.com
License: UNKNOWN
Platform: UNKNOWN
Classifier: Programming Language :: Python :: 3
Classifier: License :: OSI Approved :: MIT License
Classifier: Operating System :: OS Independent
Requires-Python: >=3.7
Requires-Dist: numpy
Requires-Dist: pandas
Requires-Dist: matplotlib
Requires-Dist: seaborn
Requires-Dist: sklearn
